azubi_timesheet/__init__.py
azubi_timesheet/azubi_timesheet.py
azubi_timesheet/timesheet.py
azubi_timesheet/data/templates/template_timesheet_19_days.xlsx
azubi_timesheet/data/templates/template_timesheet_20_days.xlsx
azubi_timesheet/data/templates/template_timesheet_21_days.xlsx
azubi_timesheet/data/templates/template_timesheet_22_days.xlsx
azubi_timesheet/data/templates/template_timesheet_23_days.xlsx
azubi_timesheet-0.9.1.dist-info/LICENSE
azubi_timesheet-0.9.1.dist-info/METADATA
azubi_timesheet-0.9.1.dist-info/WHEEL
azubi_timesheet-0.9.1.dist-info/entry_points.txt
azubi_timesheet-0.9.1.dist-info/top_level.txt
azubi_timesheet-0.9.1.dist-info/RECORD
