Metadata-Version: 2.1
Name: azubi-timesheet
Version: 0.9.1
Summary: Keep track of your work hours. Add, delete, update records. Export and print at the end of the month!
Home-page: https://github.com/eliroca/azubi-timesheet
Author: Elisei Roca
Author-email: elisei.roca@gmail.com
License: MIT
Project-URL: Bug Tracker, https://github.com/eliroca/azubi-timesheet/issues
Project-URL: Documentation, https://github.com/eliroca/azubi-timesheet/blob/master/README.md
Project-URL: Source Code, https://github.com/eliroca/azubi-timesheet
Keywords: azubi timesheet python track hours
Platform: UNKNOWN
Classifier: Programming Language :: Python
Classifier: Programming Language :: Python :: 3
Requires-Dist: openpyxl (==3.0.2)
Requires-Dist: Pillow (==6.2.1)
